astra_assistants/__init__.py
astra_assistants/astra_assistants_event_handler.py
astra_assistants/astra_assistants_manager.py
astra_assistants/async_openai_with_default_key.py
astra_assistants/mcp_openai_adapter.py
astra_assistants/openai_with_default_key.py
astra_assistants/patch.py
astra_assistants/tools/__init__.py
astra_assistants/tools/astra_data_api.py
astra_assistants/tools/cot.py
astra_assistants/tools/e2b_code_interpreter.py
astra_assistants/tools/langflow/flowgen.py
astra_assistants/tools/langflow/schema/graph.py
astra_assistants/tools/langflow/util.py
astra_assistants/tools/structured_code/__init__.py
astra_assistants/tools/structured_code/delete.py
astra_assistants/tools/structured_code/indent.py
astra_assistants/tools/structured_code/insert.py
astra_assistants/tools/structured_code/lsp/constants.py
astra_assistants/tools/structured_code/lsp/lsp_session.py
astra_assistants/tools/structured_code/lsp/session_manager.py
astra_assistants/tools/structured_code/lsp/util.py
astra_assistants/tools/structured_code/lsp/workspace_edits.py
astra_assistants/tools/structured_code/program_cache.py
astra_assistants/tools/structured_code/replace.py
astra_assistants/tools/structured_code/rewrite.py
astra_assistants/tools/structured_code/util.py
astra_assistants/tools/structured_code/write.py
astra_assistants/tools/tool_interface.py
astra_assistants/utils.py
astra_assistants-2.5.5.dist-info/METADATA
astra_assistants-2.5.5.dist-info/WHEEL
astra_assistants-2.5.5.dist-info/RECORD
