Metadata-Version: 2.3
Name: astra-assistants
Version: 2.5.5
Summary: Astra Assistants API - drop in replacement for OpenAI Assistants, powered by AstraDB
Author: phact
Author-email: estevezsebastian@gmail.com
Requires-Python: >=3.10.0,<4.0
Classifier: Programming Language :: Python :: 3
Classifier: Programming Language :: Python :: 3.10
Classifier: Programming Language :: Python :: 3.11
Classifier: Programming Language :: Python :: 3.12
Classifier: Programming Language :: Python :: 3.13
Provides-Extra: tools
Requires-Dist: aiohttp (>=3.9.4,<4.0.0)
Requires-Dist: astrapy (>=2.0.1,<3.0.0) ; extra == "tools"
Requires-Dist: boto3 (>=1.34.31,<2.0.0)
Requires-Dist: e2b (>=1.0.1,<2.0.0) ; extra == "tools"
Requires-Dist: e2b-code-interpreter (>=1.0.1,<2.0.0) ; extra == "tools"
Requires-Dist: httpx (>=0.27.0,<0.28.0)
Requires-Dist: litellm (>=1.36.0,<2.0.0)
Requires-Dist: lsprotocol (>=2023.0.1,<2024.0.0)
Requires-Dist: mcp (>=0.9.1)
Requires-Dist: openai (>=1.21.0,<2.0.0)
Requires-Dist: python-dotenv (>=1.0.1,<2.0.0)
Requires-Dist: python-lsp-jsonrpc (>=1.1.2,<2.0.0)
Requires-Dist: ruff (>=0.6.2,<9.0.0)
Requires-Dist: tree-sitter (>=0.23.0,<0.24.0)
Requires-Dist: tree-sitter-python (>=0.23.0,<0.24.0)
